autogen_watsonx_client/__init__.py
autogen_watsonx_client/client.py
autogen_watsonx_client/config.py
autogen_watsonx_client-0.0.8.dist-info/licenses/LICENSE
autogen_watsonx_client-0.0.8.dist-info/METADATA
autogen_watsonx_client-0.0.8.dist-info/WHEEL
autogen_watsonx_client-0.0.8.dist-info/top_level.txt
autogen_watsonx_client-0.0.8.dist-info/RECORD
