Metadata-Version: 2.4
Name: autogen_watsonx_client
Version: 0.0.8
Summary: This is an autogen>=0.4 extension for watsonx client integration.
License: MIT License
Keywords: autogen,agent,AI,watsonx
Classifier: Programming Language :: Python :: 3
Requires-Python: <3.13,>=3.10
License-File: LICENSE
Requires-Dist: autogen-core>=0.4.6
Requires-Dist: autogen-ext>=0.4.6
Requires-Dist: ibm-watsonx-ai>=1.2.6
Dynamic: license-file
